sentinel_2_tif/__init__.py
sentinel_2_tif/pipeline.py
sentinel_2_tif/search.py
sentinel_2_tif/spatial.py
sentinel_2_tif/temporal.py
sentinel_2_tif-0.1.1.dist-info/licenses/LICENSE
sentinel_2_tif-0.1.1.dist-info/METADATA
sentinel_2_tif-0.1.1.dist-info/WHEEL
sentinel_2_tif-0.1.1.dist-info/top_level.txt
sentinel_2_tif-0.1.1.dist-info/RECORD
