Metadata-Version: 2.4
Name: sentinel_2_tif
Version: 0.1.1
Summary: Simplified Sentinel-2 TIF generation and spatial-temporal tools
Author: Chase Kusterer
License: MIT
Requires-Python: >=3.9
License-File: LICENSE
Requires-Dist: pandas
Requires-Dist: numpy
Requires-Dist: shapely
Requires-Dist: rioxarray
Requires-Dist: pystac-client
Requires-Dist: planetary-computer
Requires-Dist: odc-stac
Requires-Dist: tqdm
Requires-Dist: rasterio
Requires-Dist: pyproj
Provides-Extra: dev
Requires-Dist: black; extra == "dev"
Requires-Dist: pytest; extra == "dev"
Dynamic: license-file
